[
    {
        "subject": "http://dbpedia.org/resource/Jeff_Bezos",
        "predicate": "http://dbpedia.org/ontology/wikiPageWikiLink",
        "object": "http://dbpedia.org/resource/Calligraphy"
    },
    {
        "subject": "http://dbpedia.org/resource/Jeff_Bezos",
        "predicate": "http://dbpedia.org/ontology/wikiPageWikiLink",
        "object": "http://dbpedia.org/resource/Cannon_Club"
    },
    {
        "subject": "http://dbpedia.org/resource/Jeff_Bezos",
        "predicate": "http://dbpedia.org/ontology/wikiPageWikiLink",
        "object": "http://dbpedia.org/resource/Cap_and_Gown_Club"
    },
    {
        "subject": "http://dbpedia.org/resource/Jeff_Bezos",
        "predicate": "http://dbpedia.org/ontology/wikiPageWikiLink",
        "object": "http://dbpedia.org/resource/Carillon"
    },
    {
        "subject": "http://dbpedia.org/resource/Jeff_Bezos",
        "predicate": "http://dbpedia.org/ontology/wikiPageWikiLink",
        "object": "http://dbpedia.org/resource/Carl_Icahn"
    },
    {
        "subject": "http://dbpedia.org/resource/Jeff_Bezos",
        "predicate": "http://dbpedia.org/ontology/wikiPageWikiLink",
        "object": "http://dbpedia.org/resource/American_Studies_(journal)"
    },
    {
        "subject": "http://dbpedia.org/resource/Jeff_Bezos",
        "predicate": "http://dbpedia.org/ontology/wikiPageWikiLink",
        "object": "http://dbpedia.org/resource/American_lower_class"
    },
    {
        "subject": "http://dbpedia.org/resource/Jeff_Bezos",
        "predicate": "http://dbpedia.org/ontology/wikiPageWikiLink",
        "object": "http://dbpedia.org/resource/American_middle_class"
    },
    {
        "subject": "http://dbpedia.org/resource/Jeff_Bezos",
        "predicate": "http://dbpedia.org/ontology/wikiPageWikiLink",
        "object": "http://dbpedia.org/resource/Category:Private_universities_and_colleges_in_New_Jersey"
    },
    {
        "subject": "http://dbpedia.org/resource/Jeff_Bezos",
        "predicate": "http://dbpedia.org/ontology/wikiPageWikiLink",
        "object": "http://dbpedia.org/resource/Bell_clapper"
    },
    {
        "subject": "http://dbpedia.org/resource/Jeff_Bezos",
        "predicate": "http://dbpedia.org/ontology/wikiPageWikiLink",
        "object": "http://dbpedia.org/resource/Bendheim_Center_for_Finance"
    },
    {
        "subject": "http://dbpedia.org/resource/Jeff_Bezos",
        "predicate": "http://dbpedia.org/ontology/wikiPageWikiLink",
        "object": "http://dbpedia.org/resource/President_of_Princeton_University"
    },
    {
        "subject": "http://dbpedia.org/resource/Jeff_Bezos",
        "predicate": "http://dbpedia.org/ontology/wikiPageWikiLink",
        "object": "http://dbpedia.org/resource/President_of_the_United_States"
    },
    {
        "subject": "http://dbpedia.org/resource/Jeff_Bezos",
        "predicate": "http://dbpedia.org/ontology/wikiPageWikiLink",
        "object": "http://dbpedia.org/resource/Prince_Moulay_Hicham_of_Morocco"
    },
    {
        "subject": "http://dbpedia.org/resource/Jeff_Bezos",
        "predicate": "http://dbpedia.org/ontology/wikiPageWikiLink",
        "object": "http://dbpedia.org/resource/Princeton,_New_Jersey"
    },
    {
        "subject": "http://dbpedia.org/resource/Jeff_Bezos",
        "predicate": "http://dbpedia.org/ontology/wikiPageWikiLink",
        "object": "http://dbpedia.org/resource/Princeton_Branch"
    },
    {
        "subject": "http://dbpedia.org/resource/Jeff_Bezos",
        "predicate": "http://dbpedia.org/ontology/wikiPageWikiLink",
        "object": "http://dbpedia.org/resource/Princeton_Charter_Club"
    },
    {
        "subject": "http://dbpedia.org/resource/Jeff_Bezos",
        "predicate": "http://dbpedia.org/ontology/wikiPageWikiLink",
        "object": "http://dbpedia.org/resource/Princeton_Law_School"
    },
    {
        "subject": "http://dbpedia.org/resource/Jeff_Bezos",
        "predicate": "http://dbpedia.org/ontology/wikiPageWikiLink",
        "object": "http://dbpedia.org/resource/Princeton_Plasma_Physics_Laboratory"
    },
    {
        "subject": "http://dbpedia.org/resource/Jeff_Bezos",
        "predicate": "http://dbpedia.org/ontology/wikiPageWikiLink",
        "object": "http://dbpedia.org/resource/Princeton_School_of_Public_and_International_Affairs"
    },
    {
        "subject": "http://dbpedia.org/resource/Jeff_Bezos",
        "predicate": "http://dbpedia.org/ontology/wikiPageWikiLink",
        "object": "http://dbpedia.org/resource/Princeton_Theological_Seminary"
    },
    {
        "subject": "http://dbpedia.org/resource/Jeff_Bezos",
        "predicate": "http://dbpedia.org/ontology/wikiPageWikiLink",
        "object": "http://dbpedia.org/resource/Princeton_Tigers"
    },
    {
        "subject": "http://dbpedia.org/resource/Jeff_Bezos",
        "predicate": "http://dbpedia.org/ontology/wikiPageWikiLink",
        "object": "http://dbpedia.org/resource/Princeton_Tigers_men's_basketball"
    },
    {
        "subject": "http://dbpedia.org/resource/Jeff_Bezos",
        "predicate": "http://dbpedia.org/ontology/wikiPageWikiLink",
        "object": "http://dbpedia.org/resource/Princeton_Tigers_men's_lacrosse"
    },
    {
        "subject": "http://dbpedia.org/resource/Jeff_Bezos",
        "predicate": "http://dbpedia.org/ontology/wikiPageWikiLink",
        "object": "http://dbpedia.org/resource/Princeton_Triangle_Club"
    },
    {
        "subject": "http://dbpedia.org/resource/Jeff_Bezos",
        "predicate": "http://dbpedia.org/ontology/wikiPageWikiLink",
        "object": "http://dbpedia.org/resource/Princeton_University_Art_Museum"
    },
    {
        "subject": "http://dbpedia.org/resource/Jeff_Bezos",
        "predicate": "http://dbpedia.org/ontology/wikiPageWikiLink",
        "object": "http://dbpedia.org/resource/Princeton_University_Band"
    },
    {
        "subject": "http://dbpedia.org/resource/Jeff_Bezos",
        "predicate": "http://dbpedia.org/ontology/wikiPageWikiLink",
        "object": "http://dbpedia.org/resource/Princeton_University_Chapel"
    },
    {
        "subject": "http://dbpedia.org/resource/Jeff_Bezos",
        "predicate": "http://dbpedia.org/ontology/wikiPageWikiLink",
        "object": "http://dbpedia.org/resource/Princeton_University_Graduate_College"
    },
    {
        "subject": "http://dbpedia.org/resource/Jeff_Bezos",
        "predicate": "http://dbpedia.org/ontology/wikiPageWikiLink",
        "object": "http://dbpedia.org/resource/Princeton_University_Library"
    },
    {
        "subject": "http://dbpedia.org/resource/Jeff_Bezos",
        "predicate": "http://dbpedia.org/ontology/wikiPageWikiLink",
        "object": "http://dbpedia.org/resource/Princeton_University_Press"
    },
    {
        "subject": "http://dbpedia.org/resource/Jeff_Bezos",
        "predicate": "http://dbpedia.org/ontology/wikiPageWikiLink",
        "object": "http://dbpedia.org/resource/Public_university"
    },
    {
        "subject": "http://dbpedia.org/resource/Jeff_Bezos",
        "predicate": "http://dbpedia.org/ontology/wikiPageWikiLink",
        "object": "http://dbpedia.org/resource/Pulitzer_Prize"
    },
    {
        "subject": "http://dbpedia.org/resource/Jeff_Bezos",
        "predicate": "http://dbpedia.org/ontology/wikiPageWikiLink",
        "object": "http://dbpedia.org/resource/QS_World_University_Rankings"
    },
    {
        "subject": "http://dbpedia.org/resource/Jeff_Bezos",
        "predicate": "http://dbpedia.org/ontology/wikiPageWikiLink",
        "object": "http://dbpedia.org/resource/Quadrangle_Club"
    },
    {
        "subject": "http://dbpedia.org/resource/Jeff_Bezos",
        "predicate": "http://dbpedia.org/ontology/wikiPageWikiLink",
        "object": "http://dbpedia.org/resource/Queen_Noor_of_Jordan"
    },
    {
        "subject": "http://dbpedia.org/resource/Jeff_Bezos",
        "predicate": "http://dbpedia.org/ontology/wikiPageWikiLink",
        "object": "http://dbpedia.org/resource/QuestBridge"
    },
    {
        "subject": "http://dbpedia.org/resource/Jeff_Bezos",
        "predicate": "http://dbpedia.org/ontology/wikiPageWikiLink",
        "object": "http://dbpedia.org/resource/Robert_P._George"
    },
    {
        "subject": "http://dbpedia.org/resource/Jeff_Bezos",
        "predicate": "http://dbpedia.org/ontology/wikiPageWikiLink",
        "object": "http://dbpedia.org/resource/Robert_Venturi"
    },
    {
        "subject": "http://dbpedia.org/resource/Jeff_Bezos",
        "predicate": "http://dbpedia.org/ontology/wikiPageWikiLink",
        "object": "http://dbpedia.org/resource/Rockefeller_College"
    },
    {
        "subject": "http://dbpedia.org/resource/Jeff_Bezos",
        "predicate": "http://dbpedia.org/ontology/wikiPageWikiLink",
        "object": "http://dbpedia.org/resource/Samuel_Alito"
    },
    {
        "subject": "http://dbpedia.org/resource/Jeff_Bezos",
        "predicate": "http://dbpedia.org/ontology/wikiPageWikiLink",
        "object": "http://dbpedia.org/resource/Samuel_Stanhope_Smith"
    },
    {
        "subject": "http://dbpedia.org/resource/Jeff_Bezos",
        "predicate": "http://dbpedia.org/ontology/wikiPageWikiLink",
        "object": "http://dbpedia.org/resource/Sarah_Lawrence_College"
    },
    {
        "subject": "http://dbpedia.org/resource/Jeff_Bezos",
        "predicate": "http://dbpedia.org/ontology/wikiPageWikiLink",
        "object": "http://dbpedia.org/resource/Scotch-Irish_Americans"
    },
    {
        "subject": "http://dbpedia.org/resource/Jeff_Bezos",
        "predicate": "http://dbpedia.org/ontology/wikiPageWikiLink",
        "object": "http://dbpedia.org/resource/List_of_colleges_and_universities_in_the_United_States_by_endowment"
    },
    {
        "subject": "http://dbpedia.org/resource/Jeff_Bezos",
        "predicate": "http://dbpedia.org/ontology/wikiPageWikiLink",
        "object": "http://dbpedia.org/resource/MD\u2013PhD"
    },
    {
        "subject": "http://dbpedia.org/resource/Jeff_Bezos",
        "predicate": "http://dbpedia.org/ontology/wikiPageWikiLink",
        "object": "http://dbpedia.org/resource/Oil_sands"
    },
    {
        "subject": "http://dbpedia.org/resource/Jeff_Bezos",
        "predicate": "http://dbpedia.org/ontology/wikiPageWikiLink",
        "object": "http://dbpedia.org/resource/Princeton_Katzenjammers"
    },
    {
        "subject": "http://dbpedia.org/resource/Jeff_Bezos",
        "predicate": "http://dbpedia.org/ontology/wikiPageWikiLink",
        "object": "http://dbpedia.org/resource/Princeton_Nassoons"
    },
    {
        "subject": "http://dbpedia.org/resource/Jeff_Bezos",
        "predicate": "http://dbpedia.org/ontology/wikiPageWikiLink",
        "object": "http://dbpedia.org/resource/Princeton_Symphony_Orchestra"
    },
    {
        "subject": "http://dbpedia.org/resource/Jeff_Bezos",
        "predicate": "http://dbpedia.org/ontology/wikiPageWikiLink",
        "object": "http://dbpedia.org/resource/Princeton_University_Department_of_Physics"
    },
    {
        "subject": "http://dbpedia.org/resource/Jeff_Bezos",
        "predicate": "http://dbpedia.org/ontology/wikiPageWikiLink",
        "object": "http://dbpedia.org/resource/Princeton_University_Graduate_School"
    },
    {
        "subject": "http://dbpedia.org/resource/Jeff_Bezos",
        "predicate": "http://dbpedia.org/ontology/wikiPageWikiLink",
        "object": "http://dbpedia.org/resource/Princeton_University_School_of_Architecture"
    },
    {
        "subject": "http://dbpedia.org/resource/Jeff_Bezos",
        "predicate": "http://dbpedia.org/ontology/wikiPageWikiLink",
        "object": "http://dbpedia.org/resource/Princeton_offense"
    },
    {
        "subject": "http://dbpedia.org/resource/Jeff_Bezos",
        "predicate": "http://dbpedia.org/ontology/wikiPageWikiLink",
        "object": "http://dbpedia.org/resource/Rutgers_Graduate_School_of_Biomedical_Sciences"
    },
    {
        "subject": "http://dbpedia.org/resource/Jeff_Bezos",
        "predicate": "http://dbpedia.org/ontology/wikiPageWikiLink",
        "object": "http://dbpedia.org/resource/Barton_Gellman"
    },
    {
        "subject": "http://dbpedia.org/resource/Jeff_Bezos",
        "predicate": "http://dbpedia.org/ontology/wikiPageWikiLink",
        "object": "http://dbpedia.org/resource/Battle_of_Princeton"
    },
    {
        "subject": "http://dbpedia.org/resource/Jeff_Bezos",
        "predicate": "http://dbpedia.org/ontology/wikiPageWikiLink",
        "object": "http://dbpedia.org/resource/Beatrix_Farrand"
    },
    {
        "subject": "http://dbpedia.org/resource/Jeff_Bezos",
        "predicate": "http://dbpedia.org/ontology/wikiPageWikiLink",
        "object": "http://dbpedia.org/resource/Ben_Bernanke"
    },
    {
        "subject": "http://dbpedia.org/resource/Jeff_Bezos",
        "predicate": "http://dbpedia.org/ontology/wikiPageWikiLink",
        "object": "http://dbpedia.org/resource/Betsy_Levy_Paluck"
    },
    {
        "subject": "http://dbpedia.org/resource/Jeff_Bezos",
        "predicate": "http://dbpedia.org/ontology/wikiPageWikiLink",
        "object": "http://dbpedia.org/resource/Bloomberg_News"
    },
    {
        "subject": "http://dbpedia.org/resource/Jeff_Bezos",
        "predicate": "http://dbpedia.org/ontology/wikiPageWikiLink",
        "object": "http://dbpedia.org/resource/Bob_Bradley"
    },
    {
        "subject": "http://dbpedia.org/resource/Jeff_Bezos",
        "predicate": "http://dbpedia.org/ontology/wikiPageWikiLink",
        "object": "http://dbpedia.org/resource/Booth_Tarkington"
    },
    {
        "subject": "http://dbpedia.org/resource/Jeff_Bezos",
        "predicate": "http://dbpedia.org/ontology/wikiPageWikiLink",
        "object": "http://dbpedia.org/resource/Brian_Kernighan"
    },
    {
        "subject": "http://dbpedia.org/resource/Jeff_Bezos",
        "predicate": "http://dbpedia.org/ontology/wikiPageWikiLink",
        "object": "http://dbpedia.org/resource/David_Duchovny"
    },
    {
        "subject": "http://dbpedia.org/resource/Jeff_Bezos",
        "predicate": "http://dbpedia.org/ontology/wikiPageWikiLink",
        "object": "http://dbpedia.org/resource/David_Mathews"
    },
    {
        "subject": "http://dbpedia.org/resource/Jeff_Bezos",
        "predicate": "http://dbpedia.org/ontology/wikiPageWikiLink",
        "object": "http://dbpedia.org/resource/David_Petraeus"
    },
    {
        "subject": "http://dbpedia.org/resource/Jeff_Bezos",
        "predicate": "http://dbpedia.org/ontology/wikiPageWikiLink",
        "object": "http://dbpedia.org/resource/David_Remnick"
    },
    {
        "subject": "http://dbpedia.org/resource/Jeff_Bezos",
        "predicate": "http://dbpedia.org/ontology/wikiPageWikiLink",
        "object": "http://dbpedia.org/resource/Denise_Scott_Brown"
    },
    {
        "subject": "http://dbpedia.org/resource/Jeff_Bezos",
        "predicate": "http://dbpedia.org/ontology/wikiPageWikiLink",
        "object": "http://dbpedia.org/resource/Category:Environmental_research_institutes"
    },
    {
        "subject": "http://dbpedia.org/resource/Jeff_Bezos",
        "predicate": "http://dbpedia.org/ontology/wikiPageWikiLink",
        "object": "http://dbpedia.org/resource/Alma_mater"
    },
    {
        "subject": "http://dbpedia.org/resource/Jeff_Bezos",
        "predicate": "http://dbpedia.org/ontology/wikiPageWikiLink",
        "object": "http://dbpedia.org/resource/Aquia_Creek_sandstone"
    },
    {
        "subject": "http://dbpedia.org/resource/Jeff_Bezos",
        "predicate": "http://dbpedia.org/ontology/wikiPageWikiLink",
        "object": "http://dbpedia.org/resource/Architecture_of_the_medieval_cathedrals_of_England"
    },
    {
        "subject": "http://dbpedia.org/resource/Jeff_Bezos",
        "predicate": "http://dbpedia.org/ontology/wikiPageWikiLink",
        "object": "http://dbpedia.org/resource/House_of_Orange-Nassau"
    },
    {
        "subject": "http://dbpedia.org/resource/Jeff_Bezos",
        "predicate": "http://dbpedia.org/ontology/wikiPageWikiLink",
        "object": "http://dbpedia.org/resource/John_Tate_(mathematician)"
    },
    {
        "subject": "http://dbpedia.org/resource/Jeff_Bezos",
        "predicate": "http://dbpedia.org/ontology/wikiPageWikiLink",
        "object": "http://dbpedia.org/resource/John_Witherspoon"
    },
    {
        "subject": "http://dbpedia.org/resource/Jeff_Bezos",
        "predicate": "http://dbpedia.org/ontology/wikiPageWikiLink",
        "object": "http://dbpedia.org/resource/John_von_Neumann"
    },
    {
        "subject": "http://dbpedia.org/resource/Jeff_Bezos",
        "predicate": "http://dbpedia.org/ontology/wikiPageWikiLink",
        "object": "http://dbpedia.org/resource/Jonathan_Belcher"
    },
    {
        "subject": "http://dbpedia.org/resource/Jeff_Bezos",
        "predicate": "http://dbpedia.org/ontology/wikiPageWikiLink",
        "object": "http://dbpedia.org/resource/Jonathan_Dickinson_(New_Jersey_minister)"
    },
    {
        "subject": "http://dbpedia.org/resource/Jeff_Bezos",
        "predicate": "http://dbpedia.org/ontology/wikiPageWikiLink",
        "object": "http://dbpedia.org/resource/Joseph_Henry"
    },
    {
        "subject": "http://dbpedia.org/resource/Jeff_Bezos",
        "predicate": "http://dbpedia.org/ontology/wikiPageWikiLink",
        "object": "http://dbpedia.org/resource/Joshua_Hall_McIlvaine"
    },
    {
        "subject": "http://dbpedia.org/resource/Jeff_Bezos",
        "predicate": "http://dbpedia.org/ontology/wikiPageWikiLink",
        "object": "http://dbpedia.org/resource/Jos\u00e9_Ferrer"
    },
    {
        "subject": "http://dbpedia.org/resource/Jeff_Bezos",
        "predicate": "http://dbpedia.org/ontology/wikiPageWikiLink",
        "object": "http://dbpedia.org/resource/Joyce_Carol_Oates"
    },
    {
        "subject": "http://dbpedia.org/resource/Jeff_Bezos",
        "predicate": "http://dbpedia.org/ontology/wikiPageWikiLink",
        "object": "http://dbpedia.org/resource/Betsey_Stockton"
    },
    {
        "subject": "http://dbpedia.org/resource/Jeff_Bezos",
        "predicate": "http://dbpedia.org/ontology/wikiPageWikiLink",
        "object": "http://dbpedia.org/resource/List_of_capitals_in_the_United_States"
    },
    {
        "subject": "http://dbpedia.org/resource/Jeff_Bezos",
        "predicate": "http://dbpedia.org/ontology/wikiPageWikiLink",
        "object": "http://dbpedia.org/resource/Paul_C\u00e9zanne"
    },
    {
        "subject": "http://dbpedia.org/resource/Jeff_Bezos",
        "predicate": "http://dbpedia.org/ontology/wikiPageWikiLink",
        "object": "http://dbpedia.org/resource/Paul_Krugman"
    },
    {
        "subject": "http://dbpedia.org/resource/Jeff_Bezos",
        "predicate": "http://dbpedia.org/ontology/wikiPageWikiLink",
        "object": "http://dbpedia.org/resource/Paul_Newman"
    },
    {
        "subject": "http://dbpedia.org/resource/Jeff_Bezos",
        "predicate": "http://dbpedia.org/ontology/wikiPageWikiLink",
        "object": "http://dbpedia.org/resource/Pedro_Pablo_Kuczynski"
    },
    {
        "subject": "http://dbpedia.org/resource/Jeff_Bezos",
        "predicate": "http://dbpedia.org/ontology/wikiPageWikiLink",
        "object": "http://dbpedia.org/resource/Pennsylvania"
    },
    {
        "subject": "http://dbpedia.org/resource/Jeff_Bezos",
        "predicate": "http://dbpedia.org/ontology/wikiPageWikiLink",
        "object": "http://dbpedia.org/resource/Pete_Carril"
    },
    {
        "subject": "http://dbpedia.org/resource/Jeff_Bezos",
        "predicate": "http://dbpedia.org/ontology/wikiPageWikiLink",
        "object": "http://dbpedia.org/resource/Pete_Conrad"
    },
    {
        "subject": "http://dbpedia.org/resource/Jeff_Bezos",
        "predicate": "http://dbpedia.org/ontology/wikiPageWikiLink",
        "object": "http://dbpedia.org/resource/Peter_Singer"
    },
    {
        "subject": "http://dbpedia.org/resource/Jeff_Bezos",
        "predicate": "http://dbpedia.org/ontology/wikiPageWikiLink",
        "object": "http://dbpedia.org/resource/Renaissance"
    },
    {
        "subject": "http://dbpedia.org/resource/Jeff_Bezos",
        "predicate": "http://dbpedia.org/ontology/wikiPageWikiLink",
        "object": "http://dbpedia.org/resource/Residential_College_7"
    },
    {
        "subject": "http://dbpedia.org/resource/Jeff_Bezos",
        "predicate": "http://dbpedia.org/ontology/wikiPageWikiLink",
        "object": "http://dbpedia.org/resource/Richard_Feynman"
    },
    {
        "subject": "http://dbpedia.org/resource/Jeff_Bezos",
        "predicate": "http://dbpedia.org/ontology/wikiPageWikiLink",
        "object": "http://dbpedia.org/resource/Richard_Serra"
    },
    {
        "subject": "http://dbpedia.org/resource/Jeff_Bezos",
        "predicate": "http://dbpedia.org/ontology/wikiPageWikiLink",
        "object": "http://dbpedia.org/resource/Rider_University"
    },
    {
        "subject": "http://dbpedia.org/resource/Jeff_Bezos",
        "predicate": "http://dbpedia.org/ontology/wikiPageWikiLink",
        "object": "http://dbpedia.org/resource/Robert_F._Goheen"
    },
    {
        "subject": "http://dbpedia.org/resource/Jeff_Bezos",
        "predicate": "http://dbpedia.org/ontology/wikiPageWikiLink",
        "object": "http://dbpedia.org/resource/Robert_Keohane"
    }
]