[
    {
        "subject": "http://dbpedia.org/resource/Samson_Abramsky",
        "predicate": "http://dbpedia.org/ontology/wikiPageWikiLink",
        "object": "http://dbpedia.org/resource/Carla_Gomes"
    },
    {
        "subject": "http://dbpedia.org/resource/Samson_Abramsky",
        "predicate": "http://dbpedia.org/ontology/wikiPageWikiLink",
        "object": "http://dbpedia.org/resource/Carnegie_Mellon_University"
    },
    {
        "subject": "http://dbpedia.org/resource/Samson_Abramsky",
        "predicate": "http://dbpedia.org/ontology/wikiPageWikiLink",
        "object": "http://dbpedia.org/resource/Benjamin_C._Pierce"
    },
    {
        "subject": "http://dbpedia.org/resource/Samson_Abramsky",
        "predicate": "http://dbpedia.org/ontology/wikiPageWikiLink",
        "object": "http://dbpedia.org/resource/Prolog"
    },
    {
        "subject": "http://dbpedia.org/resource/Samson_Abramsky",
        "predicate": "http://dbpedia.org/ontology/wikiPageWikiLink",
        "object": "http://dbpedia.org/resource/QS_World_University_Rankings"
    },
    {
        "subject": "http://dbpedia.org/resource/Samson_Abramsky",
        "predicate": "http://dbpedia.org/ontology/wikiPageWikiLink",
        "object": "http://dbpedia.org/resource/Robin_Milner"
    },
    {
        "subject": "http://dbpedia.org/resource/Samson_Abramsky",
        "predicate": "http://dbpedia.org/ontology/wikiPageWikiLink",
        "object": "http://dbpedia.org/resource/Robin_Popplestone"
    },
    {
        "subject": "http://dbpedia.org/resource/Samson_Abramsky",
        "predicate": "http://dbpedia.org/ontology/wikiPageWikiLink",
        "object": "http://dbpedia.org/resource/Rod_Burstall"
    },
    {
        "subject": "http://dbpedia.org/resource/Samson_Abramsky",
        "predicate": "http://dbpedia.org/ontology/wikiPageWikiLink",
        "object": "http://dbpedia.org/resource/Samson_Abramsky"
    },
    {
        "subject": "http://dbpedia.org/resource/Samson_Abramsky",
        "predicate": "http://dbpedia.org/ontology/wikiPageWikiLink",
        "object": "http://dbpedia.org/resource/Scotland"
    },
    {
        "subject": "http://dbpedia.org/resource/Samson_Abramsky",
        "predicate": "http://dbpedia.org/ontology/wikiPageWikiLink",
        "object": "http://dbpedia.org/resource/Elham_Kashefi"
    },
    {
        "subject": "http://dbpedia.org/resource/Samson_Abramsky",
        "predicate": "http://dbpedia.org/ontology/wikiPageWikiLink",
        "object": "http://dbpedia.org/resource/Natural_language_processing"
    },
    {
        "subject": "http://dbpedia.org/resource/Samson_Abramsky",
        "predicate": "http://dbpedia.org/ontology/wikiPageWikiLink",
        "object": "http://dbpedia.org/resource/Beihang_University"
    },
    {
        "subject": "http://dbpedia.org/resource/Samson_Abramsky",
        "predicate": "http://dbpedia.org/ontology/wikiPageWikiLink",
        "object": "http://dbpedia.org/resource/Bennetts_Associates"
    },
    {
        "subject": "http://dbpedia.org/resource/Samson_Abramsky",
        "predicate": "http://dbpedia.org/ontology/wikiPageWikiLink",
        "object": "http://dbpedia.org/resource/Bonnie_Webber"
    },
    {
        "subject": "http://dbpedia.org/resource/Samson_Abramsky",
        "predicate": "http://dbpedia.org/ontology/wikiPageWikiLink",
        "object": "http://dbpedia.org/resource/DeepMind"
    },
    {
        "subject": "http://dbpedia.org/resource/Samson_Abramsky",
        "predicate": "http://dbpedia.org/ontology/wikiPageWikiLink",
        "object": "http://dbpedia.org/resource/Alistair_Sinclair"
    },
    {
        "subject": "http://dbpedia.org/resource/Samson_Abramsky",
        "predicate": "http://dbpedia.org/ontology/wikiPageWikiLink",
        "object": "http://dbpedia.org/resource/Andrew_D._Gordon"
    },
    {
        "subject": "http://dbpedia.org/resource/Samson_Abramsky",
        "predicate": "http://dbpedia.org/ontology/wikiPageWikiLink",
        "object": "http://dbpedia.org/resource/Appleton_Tower"
    },
    {
        "subject": "http://dbpedia.org/resource/Samson_Abramsky",
        "predicate": "http://dbpedia.org/ontology/wikiPageWikiLink",
        "object": "http://dbpedia.org/resource/Johns_Hopkins_University"
    },
    {
        "subject": "http://dbpedia.org/resource/Samson_Abramsky",
        "predicate": "http://dbpedia.org/ontology/wikiPageWikiLink",
        "object": "http://dbpedia.org/resource/Peter_Buneman"
    },
    {
        "subject": "http://dbpedia.org/resource/Samson_Abramsky",
        "predicate": "http://dbpedia.org/ontology/wikiPageWikiLink",
        "object": "http://dbpedia.org/resource/Peter_Dayan"
    },
    {
        "subject": "http://dbpedia.org/resource/Samson_Abramsky",
        "predicate": "http://dbpedia.org/ontology/wikiPageWikiLink",
        "object": "http://dbpedia.org/resource/Richard_Gregory"
    },
    {
        "subject": "http://dbpedia.org/resource/Samson_Abramsky",
        "predicate": "http://dbpedia.org/ontology/wikiPageWikiLink",
        "object": "http://dbpedia.org/resource/Robert_Kowalski"
    },
    {
        "subject": "http://dbpedia.org/resource/Samson_Abramsky",
        "predicate": "http://dbpedia.org/ontology/wikiPageWikiLink",
        "object": "http://dbpedia.org/resource/University_of_Birmingham"
    },
    {
        "subject": "http://dbpedia.org/resource/Samson_Abramsky",
        "predicate": "http://dbpedia.org/ontology/wikiPageWikiLink",
        "object": "http://dbpedia.org/resource/University_of_Bologna"
    },
    {
        "subject": "http://dbpedia.org/resource/Samson_Abramsky",
        "predicate": "http://dbpedia.org/ontology/wikiPageWikiLink",
        "object": "http://dbpedia.org/resource/University_of_Bristol"
    },
    {
        "subject": "http://dbpedia.org/resource/Samson_Abramsky",
        "predicate": "http://dbpedia.org/ontology/wikiPageWikiLink",
        "object": "http://dbpedia.org/resource/University_of_California,_Berkeley"
    },
    {
        "subject": "http://dbpedia.org/resource/Samson_Abramsky",
        "predicate": "http://dbpedia.org/ontology/wikiPageWikiLink",
        "object": "http://dbpedia.org/resource/University_of_California,_Irvine"
    },
    {
        "subject": "http://dbpedia.org/resource/Samson_Abramsky",
        "predicate": "http://dbpedia.org/ontology/wikiPageWikiLink",
        "object": "http://dbpedia.org/resource/University_of_Cambridge"
    },
    {
        "subject": "http://dbpedia.org/resource/Samson_Abramsky",
        "predicate": "http://dbpedia.org/ontology/wikiPageWikiLink",
        "object": "http://dbpedia.org/resource/University_of_Edinburgh"
    },
    {
        "subject": "http://dbpedia.org/resource/Samson_Abramsky",
        "predicate": "http://dbpedia.org/ontology/wikiPageWikiLink",
        "object": "http://dbpedia.org/resource/University_of_London"
    },
    {
        "subject": "http://dbpedia.org/resource/Samson_Abramsky",
        "predicate": "http://dbpedia.org/ontology/wikiPageWikiLink",
        "object": "http://dbpedia.org/resource/University_of_New_South_Wales"
    },
    {
        "subject": "http://dbpedia.org/resource/Samson_Abramsky",
        "predicate": "http://dbpedia.org/ontology/wikiPageWikiLink",
        "object": "http://dbpedia.org/resource/University_of_Oxford"
    },
    {
        "subject": "http://dbpedia.org/resource/Samson_Abramsky",
        "predicate": "http://dbpedia.org/ontology/wikiPageWikiLink",
        "object": "http://dbpedia.org/resource/University_of_Pennsylvania"
    },
    {
        "subject": "http://dbpedia.org/resource/Samson_Abramsky",
        "predicate": "http://dbpedia.org/ontology/wikiPageWikiLink",
        "object": "http://dbpedia.org/resource/University_of_Texas_at_Austin"
    },
    {
        "subject": "http://dbpedia.org/resource/Samson_Abramsky",
        "predicate": "http://dbpedia.org/ontology/wikiPageWikiLink",
        "object": "http://dbpedia.org/resource/Ursula_Martin"
    },
    {
        "subject": "http://dbpedia.org/resource/Samson_Abramsky",
        "predicate": "http://dbpedia.org/ontology/wikiPageWikiLink",
        "object": "http://dbpedia.org/resource/VMware"
    },
    {
        "subject": "http://dbpedia.org/resource/Samson_Abramsky",
        "predicate": "http://dbpedia.org/ontology/wikiPageWikiLink",
        "object": "http://dbpedia.org/resource/David_H._D._Warren"
    },
    {
        "subject": "http://dbpedia.org/resource/Samson_Abramsky",
        "predicate": "http://dbpedia.org/ontology/wikiPageWikiLink",
        "object": "http://dbpedia.org/resource/Davide_Sangiorgi"
    },
    {
        "subject": "http://dbpedia.org/resource/Samson_Abramsky",
        "predicate": "http://dbpedia.org/ontology/wikiPageWikiLink",
        "object": "http://dbpedia.org/resource/Don_Sannella"
    },
    {
        "subject": "http://dbpedia.org/resource/Samson_Abramsky",
        "predicate": "http://dbpedia.org/ontology/wikiPageWikiLink",
        "object": "http://dbpedia.org/resource/Informatics"
    },
    {
        "subject": "http://dbpedia.org/resource/Samson_Abramsky",
        "predicate": "http://dbpedia.org/ontology/wikiPageWikiLink",
        "object": "http://dbpedia.org/resource/Informatics_Forum"
    },
    {
        "subject": "http://dbpedia.org/resource/Samson_Abramsky",
        "predicate": "http://dbpedia.org/ontology/wikiPageWikiLink",
        "object": "http://dbpedia.org/resource/Johanna_Moore"
    },
    {
        "subject": "http://dbpedia.org/resource/Samson_Abramsky",
        "predicate": "http://dbpedia.org/ontology/wikiPageWikiLink",
        "object": "http://dbpedia.org/resource/Lighthill_report"
    },
    {
        "subject": "http://dbpedia.org/resource/Samson_Abramsky",
        "predicate": "http://dbpedia.org/ontology/wikiPageWikiLink",
        "object": "http://dbpedia.org/resource/Lincoln_Wallen"
    },
    {
        "subject": "http://dbpedia.org/resource/Samson_Abramsky",
        "predicate": "http://dbpedia.org/ontology/wikiPageWikiLink",
        "object": "http://dbpedia.org/resource/Computer_Laboratory,_University_of_Cambridge"
    },
    {
        "subject": "http://dbpedia.org/resource/Samson_Abramsky",
        "predicate": "http://dbpedia.org/ontology/wikiPageWikiLink",
        "object": "http://dbpedia.org/resource/Cornell_University"
    },
    {
        "subject": "http://dbpedia.org/resource/Samson_Abramsky",
        "predicate": "http://dbpedia.org/ontology/wikiPageWikiLink",
        "object": "http://dbpedia.org/resource/Cowgate"
    },
    {
        "subject": "http://dbpedia.org/resource/Samson_Abramsky",
        "predicate": "http://dbpedia.org/ontology/wikiPageWikiLink",
        "object": "http://dbpedia.org/resource/Mathematical_logic"
    },
    {
        "subject": "http://dbpedia.org/resource/Samson_Abramsky",
        "predicate": "http://dbpedia.org/ontology/wikiPageWikiLink",
        "object": "http://dbpedia.org/resource/Chief_technology_officer"
    },
    {
        "subject": "http://dbpedia.org/resource/Samson_Abramsky",
        "predicate": "http://dbpedia.org/ontology/wikiPageWikiLink",
        "object": "http://dbpedia.org/resource/Michael_O'Boyle"
    },
    {
        "subject": "http://dbpedia.org/resource/Samson_Abramsky",
        "predicate": "http://dbpedia.org/ontology/wikiPageWikiLink",
        "object": "http://dbpedia.org/resource/QCDOC"
    },
    {
        "subject": "http://dbpedia.org/resource/Samson_Abramsky",
        "predicate": "http://dbpedia.org/ontology/wikiPageWikiLink",
        "object": "http://dbpedia.org/resource/Christopher_Bishop"
    },
    {
        "subject": "http://dbpedia.org/resource/Samson_Abramsky",
        "predicate": "http://dbpedia.org/ontology/wikiPageWikiLink",
        "object": "http://dbpedia.org/resource/Christopher_Longuet-Higgins"
    },
    {
        "subject": "http://dbpedia.org/resource/Samson_Abramsky",
        "predicate": "http://dbpedia.org/ontology/wikiPageWikiLink",
        "object": "http://dbpedia.org/resource/Freenet"
    },
    {
        "subject": "http://dbpedia.org/resource/Samson_Abramsky",
        "predicate": "http://dbpedia.org/ontology/wikiPageWikiLink",
        "object": "http://dbpedia.org/resource/Geoffrey_Hinton"
    },
    {
        "subject": "http://dbpedia.org/resource/Samson_Abramsky",
        "predicate": "http://dbpedia.org/ontology/wikiPageWikiLink",
        "object": "http://dbpedia.org/resource/Google_Maps"
    },
    {
        "subject": "http://dbpedia.org/resource/Samson_Abramsky",
        "predicate": "http://dbpedia.org/ontology/wikiPageWikiLink",
        "object": "http://dbpedia.org/resource/Gordon_Plotkin"
    },
    {
        "subject": "http://dbpedia.org/resource/Samson_Abramsky",
        "predicate": "http://dbpedia.org/ontology/wikiPageWikiLink",
        "object": "http://dbpedia.org/resource/Brain\u2013computer_interface"
    },
    {
        "subject": "http://dbpedia.org/resource/Samson_Abramsky",
        "predicate": "http://dbpedia.org/ontology/wikiPageWikiLink",
        "object": "http://dbpedia.org/resource/Monad_(functional_programming)"
    },
    {
        "subject": "http://dbpedia.org/resource/Samson_Abramsky",
        "predicate": "http://dbpedia.org/ontology/wikiPageWikiLink",
        "object": "http://dbpedia.org/resource/Moses_(machine_translation)"
    },
    {
        "subject": "http://dbpedia.org/resource/Samson_Abramsky",
        "predicate": "http://dbpedia.org/ontology/wikiPageWikiLink",
        "object": "http://dbpedia.org/resource/NPL_(programming_language)"
    },
    {
        "subject": "http://dbpedia.org/resource/Samson_Abramsky",
        "predicate": "http://dbpedia.org/ontology/wikiPageWikiLink",
        "object": "http://dbpedia.org/resource/Crystallography"
    },
    {
        "subject": "http://dbpedia.org/resource/Samson_Abramsky",
        "predicate": "http://dbpedia.org/ontology/wikiPageWikiLink",
        "object": "http://dbpedia.org/resource/Andrew_Blake_(scientist)"
    },
    {
        "subject": "http://dbpedia.org/resource/Samson_Abramsky",
        "predicate": "http://dbpedia.org/ontology/wikiPageWikiLink",
        "object": "http://dbpedia.org/resource/Andrew_Zisserman"
    },
    {
        "subject": "http://dbpedia.org/resource/Samson_Abramsky",
        "predicate": "http://dbpedia.org/ontology/wikiPageWikiLink",
        "object": "http://dbpedia.org/resource/Leslie_Ann_Goldberg"
    },
    {
        "subject": "http://dbpedia.org/resource/Samson_Abramsky",
        "predicate": "http://dbpedia.org/ontology/wikiPageWikiLink",
        "object": "http://dbpedia.org/resource/Leslie_Valiant"
    },
    {
        "subject": "http://dbpedia.org/resource/Samson_Abramsky",
        "predicate": "http://dbpedia.org/ontology/wikiPageWikiLink",
        "object": "http://dbpedia.org/resource/Li-Fi"
    },
    {
        "subject": "http://dbpedia.org/resource/Samson_Abramsky",
        "predicate": "http://dbpedia.org/ontology/wikiPageWikiLink",
        "object": "http://dbpedia.org/resource/Li_Wei_(computer_scientist)"
    },
    {
        "subject": "http://dbpedia.org/resource/Samson_Abramsky",
        "predicate": "http://dbpedia.org/ontology/wikiPageWikiLink",
        "object": "http://dbpedia.org/resource/Luca_Cardelli"
    },
    {
        "subject": "http://dbpedia.org/resource/Samson_Abramsky",
        "predicate": "http://dbpedia.org/ontology/wikiPageWikiLink",
        "object": "http://dbpedia.org/resource/ML_(programming_language)"
    },
    {
        "subject": "http://dbpedia.org/resource/Samson_Abramsky",
        "predicate": "http://dbpedia.org/ontology/wikiPageWikiLink",
        "object": "http://dbpedia.org/resource/Machine_Translation"
    },
    {
        "subject": "http://dbpedia.org/resource/Samson_Abramsky",
        "predicate": "http://dbpedia.org/ontology/wikiPageWikiLink",
        "object": "http://dbpedia.org/resource/Mads_Tofte"
    },
    {
        "subject": "http://dbpedia.org/resource/Samson_Abramsky",
        "predicate": "http://dbpedia.org/ontology/wikiPageWikiLink",
        "object": "http://dbpedia.org/resource/Malcolm_Atkinson"
    },
    {
        "subject": "http://dbpedia.org/resource/Samson_Abramsky",
        "predicate": "http://dbpedia.org/ontology/wikiPageWikiLink",
        "object": "http://dbpedia.org/resource/Stephen_Muggleton"
    },
    {
        "subject": "http://dbpedia.org/resource/Samson_Abramsky",
        "predicate": "http://dbpedia.org/ontology/wikiPageWikiLink",
        "object": "http://dbpedia.org/resource/Computational_linguistics"
    },
    {
        "subject": "http://dbpedia.org/resource/Samson_Abramsky",
        "predicate": "http://dbpedia.org/ontology/wikiPageWikiLink",
        "object": "http://dbpedia.org/resource/\u00c9cole_Polytechnique_F\u00e9d\u00e9rale_de_Lausanne"
    },
    {
        "subject": "http://dbpedia.org/resource/Samson_Abramsky",
        "predicate": "http://dbpedia.org/ontology/wikiPageWikiLink",
        "object": "http://dbpedia.org/resource/Frank_Keller"
    },
    {
        "subject": "http://dbpedia.org/resource/Samson_Abramsky",
        "predicate": "http://dbpedia.org/ontology/wikiPageWikiLink",
        "object": "http://dbpedia.org/resource/Full-time_equivalent"
    },
    {
        "subject": "http://dbpedia.org/resource/Samson_Abramsky",
        "predicate": "http://dbpedia.org/ontology/wikiPageWikiLink",
        "object": "http://dbpedia.org/resource/Hennessy\u2013Milner_logic"
    },
    {
        "subject": "http://dbpedia.org/resource/Samson_Abramsky",
        "predicate": "http://dbpedia.org/ontology/wikiPageWikiLink",
        "object": "http://dbpedia.org/resource/Hope_(programming_language)"
    },
    {
        "subject": "http://dbpedia.org/resource/Samson_Abramsky",
        "predicate": "http://dbpedia.org/ontology/wikiPageWikiLink",
        "object": "http://dbpedia.org/resource/Horn_clause"
    },
    {
        "subject": "http://dbpedia.org/resource/Samson_Abramsky",
        "predicate": "http://dbpedia.org/ontology/wikiPageWikiLink",
        "object": "http://dbpedia.org/resource/Igor_Goryanin"
    },
    {
        "subject": "http://dbpedia.org/resource/Samson_Abramsky",
        "predicate": "http://dbpedia.org/ontology/wikiPageWikiLink",
        "object": "http://dbpedia.org/resource/Kousha_Etessami"
    },
    {
        "subject": "http://dbpedia.org/resource/Samson_Abramsky",
        "predicate": "http://dbpedia.org/ontology/wikiPageWikiLink",
        "object": "http://dbpedia.org/resource/Leonid_Libkin"
    },
    {
        "subject": "http://dbpedia.org/resource/Samson_Abramsky",
        "predicate": "http://dbpedia.org/ontology/wikiPageWikiLink",
        "object": "http://dbpedia.org/resource/Mark_Steedman"
    },
    {
        "subject": "http://dbpedia.org/resource/Samson_Abramsky",
        "predicate": "http://dbpedia.org/ontology/wikiPageWikiLink",
        "object": "http://dbpedia.org/resource/Theoretical_computer_science"
    },
    {
        "subject": "http://dbpedia.org/resource/Samson_Abramsky",
        "predicate": "http://dbpedia.org/ontology/wikiPageWikiLink",
        "object": "http://dbpedia.org/resource/Mark_Jerrum"
    },
    {
        "subject": "http://dbpedia.org/resource/Samson_Abramsky",
        "predicate": "http://dbpedia.org/ontology/wikiPageWikiLink",
        "object": "http://dbpedia.org/resource/Matthew_Hennessy"
    },
    {
        "subject": "http://dbpedia.org/resource/Samson_Abramsky",
        "predicate": "http://dbpedia.org/ontology/wikiPageWikiLink",
        "object": "http://dbpedia.org/resource/Max_Planck_Institute_for_Biological_Cybernetics"
    },
    {
        "subject": "http://dbpedia.org/resource/Samson_Abramsky",
        "predicate": "http://dbpedia.org/ontology/wikiPageWikiLink",
        "object": "http://dbpedia.org/resource/PropBank"
    },
    {
        "subject": "http://dbpedia.org/resource/Samson_Abramsky",
        "predicate": "http://dbpedia.org/ontology/wikiPageWikiLink",
        "object": "http://dbpedia.org/resource/Auke_Ijspeert"
    },
    {
        "subject": "http://dbpedia.org/resource/Samson_Abramsky",
        "predicate": "http://dbpedia.org/ontology/wikiPageWikiLink",
        "object": "http://dbpedia.org/resource/Austin_Tate"
    },
    {
        "subject": "http://dbpedia.org/resource/Samson_Abramsky",
        "predicate": "http://dbpedia.org/ontology/wikiPageWikiLink",
        "object": "http://dbpedia.org/resource/CERN"
    },
    {
        "subject": "http://dbpedia.org/resource/Samson_Abramsky",
        "predicate": "http://dbpedia.org/ontology/wikiPageWikiLink",
        "object": "http://dbpedia.org/resource/COWSEL"
    },
    {
        "subject": "http://dbpedia.org/resource/Samson_Abramsky",
        "predicate": "http://dbpedia.org/ontology/wikiPageWikiLink",
        "object": "http://dbpedia.org/resource/Aggelos_Kiayias"
    },
    {
        "subject": "http://dbpedia.org/resource/Samson_Abramsky",
        "predicate": "http://dbpedia.org/ontology/wikiPageWikiLink",
        "object": "http://dbpedia.org/resource/Timothy_O'Shea"
    },
    {
        "subject": "http://dbpedia.org/resource/Samson_Abramsky",
        "predicate": "http://dbpedia.org/ontology/wikiPageWikiLink",
        "object": "http://dbpedia.org/resource/Turing_Award"
    },
    {
        "subject": "http://dbpedia.org/resource/Samson_Abramsky",
        "predicate": "http://dbpedia.org/ontology/wikiPageWikiLink",
        "object": "http://dbpedia.org/resource/Wenfei_Fan"
    }
]